pywriter/__init__.py
pywriter/__main__.py
pywriter-2.0.0.dist-info/METADATA
pywriter-2.0.0.dist-info/WHEEL
pywriter-2.0.0.dist-info/entry_points.txt
pywriter-2.0.0.dist-info/licenses/LICENSE
pywriter-2.0.0.dist-info/RECORD
