Metadata-Version: 2.4
Name: pywriter
Version: 2.0.0
Summary: Typewriter effect for python.
Project-URL: Homepage, https://github.com/amarquaye/pywriter
Project-URL: Issues, https://github.com/amarquaye/pywriter/issues
Project-URL: Documentation, https://amarquaye.github.io/pywriter/
Project-URL: Repository, https://github.com/amarquaye/pywriter.git
Project-URL: Changelog, https://github.com/amarquaye/pywriter/blob/master/CHANGELOG
Author-email: Jesse Amarquaye <engineeramarquaye@gmail.com>
Maintainer-email: Jesse Amarquaye <engineeramarquaye@gmail.com>
License: MIT License
License-File: LICENSE
Keywords: animation,python,pywriter,type,typewriter,typewriter animation,typewriter effect,writer
Classifier: Development Status :: 5 - Production/Stable
Classifier: Environment :: Console
Classifier: Intended Audience :: Developers
Classifier: License :: OSI Approved :: MIT License
Classifier: Operating System :: OS Independent
Classifier: Programming Language :: Python :: 3
Classifier: Topic :: Printing
Classifier: Topic :: Terminals
Classifier: Topic :: Text Processing
Requires-Python: >=3.3
